{
  "data_asset_type": null,
  "expectation_suite_name": "raw_transaction_expectation_suite",
  "expectations": [
    {
      "expectation_type": "expect_column_values_to_not_be_null",
      "kwargs": {
        "column": "trans_num"
      },
      "meta": {}
    },
    {
      "expectation_type": "expect_column_values_to_not_be_null",
      "kwargs": {
        "column": "cc_num"
      },
      "meta": {}
    },
    {
      "expectation_type": "expect_column_values_to_be_unique",
      "kwargs": {
        "column": "trans_num"
      },
      "meta": {}
    },
    {
      "expectation_type": "expect_column_values_to_be_of_type",
      "kwargs": {
        "column": "amt",
        "type_": "float"
      },
      "meta": {}
    },
    {
      "expectation_type": "expect_column_values_to_be_between",
      "kwargs": {
        "column": "amt",
        "max_value": 100000,
        "min_value": 0,
        "mostly": 0.999
      },
      "meta": {}
    },
    {
      "expectation_type": "expect_column_values_to_be_in_set",
      "kwargs": {
        "column": "is_fraud",
        "value_set": [
          0,
          1,
          true,
          false
        ]
      },
      "meta": {}
    }
  ],
  "ge_cloud_id": null,
  "meta": {
    "great_expectations_version": "0.18.19"
  }
}